scd_type2/__init__.py
scd_type2/compare.py
scd_type2/config.py
scd_type2/utils.py
tests/__init__.py
tests/test_compare_df.py
scd_type2-0.1.1.dist-info/METADATA
scd_type2-0.1.1.dist-info/WHEEL
scd_type2-0.1.1.dist-info/entry_points.txt
scd_type2-0.1.1.dist-info/top_level.txt
scd_type2-0.1.1.dist-info/RECORD
